benchgrape/__init__.py
benchgrape/bootstrap.py
benchgrape/config.py
benchgrape/main.py
benchgrape/controllers/__init__.py
benchgrape/controllers/benchmark.py
benchgrape/controllers/test_data.py
benchgrape/core/__init__.py
benchgrape/core/db.py
benchgrape/core/exc.py
benchgrape/core/lp.py
benchgrape/core/statement.py
benchgrape/core/utils.py
benchgrape/core/version.py
benchgrape/core/wamp.py
benchgrape/ext/__init__.py
benchgrape/locust/__init__.py
benchgrape/locust/locustfiles/__init__.py
benchgrape/locust/locustfiles/locustfile.py
benchgrape/locust/locustfiles/stability.py
benchgrape/plugins/__init__.py
benchgrape/templates/__init__.py
benchgrape/templates/command1.jinja2
benchgrape-0.0.13.dev20200328175058.dist-info/LICENSE.md
benchgrape-0.0.13.dev20200328175058.dist-info/METADATA
benchgrape-0.0.13.dev20200328175058.dist-info/WHEEL
benchgrape-0.0.13.dev20200328175058.dist-info/entry_points.txt
benchgrape-0.0.13.dev20200328175058.dist-info/top_level.txt
benchgrape-0.0.13.dev20200328175058.dist-info/RECORD
