Metadata-Version: 2.1
Name: benchgrape
Version: 0.0.13.dev20200328175058
Summary: This is how you'd Bench a Grape!
Home-page: https://gitlab.chatgrape.com/salzamt/benchgrape
Author: Riccardo Salzer
Author-email: beschwerden@salzamt.xyz
License: MIT
Platform: UNKNOWN
Requires-Dist: cement (==3.0.2)
Requires-Dist: locustio
Requires-Dist: websocket-client
Requires-Dist: jinja2
Requires-Dist: pyyaml
Requires-Dist: colorlog
